mesoscopy/__about__.py
mesoscopy/__init__.py
mesoscopy/io.py
mesoscopy/plots.py
mesoscopy/timer.py
mesoscopy/convert/__init__.py
mesoscopy/convert/hdf5.py
mesoscopy/convert/metadata.py
mesoscopy/convert/video.py
mesoscopy/export/__init__.py
mesoscopy/export/nwb.py
mesoscopy/inspect/__init__.py
mesoscopy/inspect/data_viewers.py
mesoscopy/postprocess/__init__.py
mesoscopy/preprocess/__init__.py
mesoscopy/preprocess/compute.py
mesoscopy/preprocess/qa.py
mesoscopy/process/__init__.py
mesoscopy/process/smooth.py
mesoscopy/process/zscore.py
mesoscopy/register/__init__.py
mesoscopy/register/landmarks_gui.py
mesoscopy/register/qa.py
mesoscopy/register/transform.py
mesoscopy/report/__init__.py
mesoscopy/report/templates/base.html
mesoscopy/report/templates/preprocessing.html
mesoscopy/report/templates/registration.html
mesoscopy/resources/__init__.py
mesoscopy/resources/ccf_annotations.csv
mesoscopy/resources/ccf_template_landmarks_140x142.csv
mesoscopy/resources/ccf_template_top_140x142.points
mesoscopy/resources/ccf_template_top_140x142.tiff
mesoscopy-0.7.4.dist-info/METADATA
mesoscopy-0.7.4.dist-info/WHEEL
mesoscopy-0.7.4.dist-info/entry_points.txt
mesoscopy-0.7.4.dist-info/licenses/LICENSE
mesoscopy-0.7.4.dist-info/RECORD
