Metadata-Version: 2.4
Name: mesoscopy
Version: 0.7.4
Summary: Analysis pipeline for rodent widefield calcium imaging data.
Project-URL: Issues, https://github.com/DuguidLab/mesoscopy/issues
Project-URL: Source, https://github.com/DuguidLab/mesoscopy
Author-email: Constantinos Eleftheriou <Constantinos.Eleftheriou@ed.ac.uk>
License: MIT License
License-File: LICENSE
Keywords: behaviour,imaging,neuroscience,widefield
Classifier: Development Status :: 2 - Pre-Alpha
Classifier: Intended Audience :: Science/Research
Classifier: License :: OSI Approved :: MIT License
Classifier: Programming Language :: Python :: 3.12
Classifier: Topic :: Scientific/Engineering
Requires-Python: >=3.12
Requires-Dist: av>=14.4.0
Requires-Dist: click
Requires-Dist: dask-image>=2021.12.0
Requires-Dist: dask>=2021.4.1
Requires-Dist: diptest
Requires-Dist: graphviz
Requires-Dist: h5py>=3.6.0
Requires-Dist: imageio[ffmpeg]
Requires-Dist: jinja2
Requires-Dist: matplotlib
Requires-Dist: napari>=0.4.19
Requires-Dist: numpy>=1.21.2
Requires-Dist: pandas
Requires-Dist: pims>=0.7
Requires-Dist: plotly
Requires-Dist: pynwb<3,>=2.3.1
Requires-Dist: pyqt5
Requires-Dist: scikit-image
Requires-Dist: scikit-video
Requires-Dist: scipy>=1.7.1
Requires-Dist: tables
Requires-Dist: xmltodict
Requires-Dist: zarr<3,>=2
